pycolorutils/FancyTable.py
pycolorutils/__init__.py
pycolorutils/color.py
pycolorutils/reader.py
pycolorutils-1.2.5.dist-info/LICENSE
pycolorutils-1.2.5.dist-info/METADATA
pycolorutils-1.2.5.dist-info/WHEEL
pycolorutils-1.2.5.dist-info/top_level.txt
pycolorutils-1.2.5.dist-info/RECORD
