Metadata-Version: 2.2
Name: pycolorutils
Version: 1.2.5
Summary: A set of useful utilities for Python
Author-email: Pecacheu <3608878+Pecacheu@users.noreply.github.com>
Project-URL: Homepage, https://github.com/Pecacheu/PyColor
Project-URL: Issues, https://github.com/Pecacheu/PyColor/issues
Classifier: Programming Language :: Python :: 3
Classifier: License :: OSI Approved :: MIT License
Classifier: Operating System :: Microsoft :: Windows
Classifier: Operating System :: POSIX :: Linux
Requires-Python: >=3.10
License-File: LICENSE
